pyhannom/__init__.py
pyhannom/data_store.py
pyhannom/func_test.py
pyhannom/func_test_demo.py
pyhannom/get_chuhannom_from_latin.py
pyhannom/get_chuhannom_word_from_latin.py
pyhannom/get_latin_from_chuhannom.py
pyhannom/get_latin_word_from_chuhannom.py
pyhannom/hannom_to_latin.py
pyhannom/latin_to_hannom.py
pyhannom/load_extend_hannom_table.py
pyhannom/load_hannom_table.py
pyhannom/load_parallel_corpus.py
pyhannom/load_syllable_char_table.py
pyhannom/load_word_table.py
pyhannom/data/260109_lookup_html.txt
pyhannom/data/GungJyuChaJiouZiiHanNanZhuen_new_v1.csv
pyhannom/data/GungJyuChaJiouZiiHanNanZhuen_raw.csv
pyhannom/data/country_name.txt
pyhannom/data/mapping_data.js
pyhannom/data/note.txt
pyhannom/data/parallel_corpus.json
pyhannom/data/raw_char_word_table.txt
pyhannom/data/vietnam_province_name.txt
pyhannom-0.2.0.dist-info/LICENSE
pyhannom-0.2.0.dist-info/METADATA
pyhannom-0.2.0.dist-info/WHEEL
pyhannom-0.2.0.dist-info/top_level.txt
pyhannom-0.2.0.dist-info/RECORD
