Metadata-Version: 2.1
Name: pyhannom
Version: 0.2.0
Summary: A Python toolkit for the digitization of Han-Nom characters, enabling AI and natural language processing applications with Vietnamese Han-Nom data.
Author-email: Zijie ZHANG <zijiezhang@link.cuhk.edu.hk>
License: MIT License (for code)
Project-URL: Homepage, https://pypi.org/project/pyhannom/
Requires-Python: >=3.7
License-File: LICENSE
